killdupes-0.1.6.data/scripts/killdupes.py
tests/__init__.py
tests/test_killdupes.py
killdupes-0.1.6.dist-info/WHEEL
killdupes-0.1.6.dist-info/pydist.json
killdupes-0.1.6.dist-info/RECORD
killdupes-0.1.6.dist-info/DESCRIPTION.rst
killdupes-0.1.6.dist-info/METADATA
killdupes-0.1.6.dist-info/top_level.txt
killdupes/__init__.py
killdupes/killdupes.py
